LICENSE.txt
MANIFEST.in
README.rst
requirements.txt
setup.py
slack_groupmgr/__init__.py
slack_groupmgr/cgifront.py
slack_groupmgr/cmdline.py
slack_groupmgr/flask.py
slack_groupmgr.egg-info/PKG-INFO
slack_groupmgr.egg-info/SOURCES.txt
slack_groupmgr.egg-info/dependency_links.txt
slack_groupmgr.egg-info/entry_points.txt
slack_groupmgr.egg-info/not-zip-safe
slack_groupmgr.egg-info/requires.txt
slack_groupmgr.egg-info/top_level.txt
slack_groupmgr/examples/config.json
slack_groupmgr/examples/groupmgr.wsgi