Metadata-Version: 1.1
Name: slack-groupmgr
Version: 1.0.3
Summary: manage private group membership
Home-page: https://gitlab.com/pleasantone/slack-groupmgr
Author: Paul Traina
Author-email: bulk+pypi@pst.org
License: UNKNOWN
Platform: UNKNOWN
Classifier: Development Status :: 5 - Production/Stable
Classifier: Environment :: Console
Classifier: Environment :: Web Environment
Classifier: License :: OSI Approved :: GNU Affero General Public License v3 or later (AGPLv3+)
Classifier: Natural Language :: English
Classifier: Operating System :: POSIX
Classifier: Programming Language :: Python :: 3.4
Classifier: Programming Language :: Python :: 3.5
Classifier: Topic :: Communications :: Chat
Classifier: Topic :: Office/Business :: Groupware
